amari/__init__.py
amari/api.py
amari/exceptions.py
amari/objects.py
simple_amari.py-1.0.0.dist-info/LICENSE
simple_amari.py-1.0.0.dist-info/METADATA
simple_amari.py-1.0.0.dist-info/WHEEL
simple_amari.py-1.0.0.dist-info/top_level.txt
simple_amari.py-1.0.0.dist-info/RECORD
