Metadata-Version: 2.1
Name: simple-amari.py
Version: 1.0.0
Summary: A simple easy2use Python wrapper for the AmariBot API.
Home-page: https://github.com/InvalidLenni/simple-amari.py
Author: InvalidLenni
License: MIT
Project-URL: Documentation, https://simple-amaripy.readthedocs.io/en/latest/
Platform: UNKNOWN
Classifier: Development Status :: 5 - Production/Stable
Classifier: Intended Audience :: Developers
Classifier: License :: OSI Approved :: MIT License
Classifier: Programming Language :: Python :: 3.8
Classifier: Programming Language :: Python :: 3.9
Requires-Python: >=3.8
License-File: LICENSE
Requires-Dist: aiohttp (<3.8.0,>=3.6.0)
